confclasses/__init__.py
confclasses/exceptions.py
confclasses-1.0.0.dist-info/licenses/LICENCE
confclasses-1.0.0.dist-info/METADATA
confclasses-1.0.0.dist-info/WHEEL
confclasses-1.0.0.dist-info/top_level.txt
confclasses-1.0.0.dist-info/RECORD
