Metadata-Version: 2.4
Name: confclasses
Version: 1.0.0
Summary: A simple wrapper around dataclasses, for general configuration
Author-email: Simon Fletcher <simon.fletcher@lexisnexisrisk.com>
License: MIT License
Project-URL: Homepage, https://github.com/simonfletcher-ln/confclasses
Project-URL: Issues, https://github.com/simonfletcher-ln/confclasses/issues
Classifier: Programming Language :: Python :: 3
Classifier: Operating System :: OS Independent
Classifier: License :: OSI Approved :: MIT License
Requires-Python: >=3.8
License-File: LICENCE
Requires-Dist: ruamel.yaml
Dynamic: license-file
